_pyterminalsize.cpython-35m-x86_64-linux-gnu.so
pyterminalsize.py
pyterminalsize-0.1.0.dist-info/WHEEL
pyterminalsize-0.1.0.dist-info/top_level.txt
pyterminalsize-0.1.0.dist-info/DESCRIPTION.rst
pyterminalsize-0.1.0.dist-info/METADATA
pyterminalsize-0.1.0.dist-info/RECORD
pyterminalsize-0.1.0.dist-info/metadata.json
