Metadata-Version: 2.0
Name: pyterminalsize
Version: 0.1.0
Summary: Determines terminal size in a cross-platform way.
Home-page: https://github.com/asottile/pyterminalsize
Author: Anthony Sottile
Author-email: asottile@umich.edu
License: UNKNOWN
Platform: UNKNOWN
Classifier: License :: OSI Approved :: MIT License
Classifier: Programming Language :: Python :: 2
Classifier: Programming Language :: Python :: 2.6
Classifier: Programming Language :: Python :: 2.7
Classifier: Programming Language :: Python :: 3
Classifier: Programming Language :: Python :: 3.3
Classifier: Programming Language :: Python :: 3.4
Classifier: Programming Language :: Python :: Implementation :: CPython
Classifier: Programming Language :: Python :: Implementation :: PyPy
